gv_linalg/__init__.py
gv_linalg/gv_linalg.py
gv_linalg-0.1.7.dist-info/METADATA
gv_linalg-0.1.7.dist-info/WHEEL
gv_linalg-0.1.7.dist-info/RECORD
